{
  "direction_a": [
    {
      "id": "_1",
      "label": "Устаничка",
      "longitude": 20.517384,
      "latitude": 44.784813
    },
    {
      "id": "_2",
      "label": "Бајдина",
      "longitude": 20.525767,
      "latitude": 44.779394
    },
    {
      "id": "_3",
      "label": "Миријевска",
      "longitude": 20.529854,
      "latitude": 44.777704
    },
    {
      "id": "_4",
      "label": "ОШ Драгојло Дудић",
      "longitude": 20.534686,
      "latitude": 44.775345
    },
    {
      "id": "_5",
      "label": "Нине Кирсанове",
      "longitude": 20.547837,
      "latitude": 44.776352
    },
    {
      "id": "_6",
      "label": "Ново Насеље",
      "longitude": 20.554095,
      "latitude": 44.772432
    },
    {
      "id": "_7",
      "label": "Пут за Калуђерицу",
      "longitude": 20.560379,
      "latitude": 44.76769
    },
    {
      "id": "_8",
      "label": "Пут за Институт",
      "longitude": 20.564336,
      "latitude": 44.764531
    },
    {
      "id": "_9",
      "label": "Филипа Кљајића",
      "longitude": 20.566266,
      "latitude": 44.762054
    },
    {
      "id": "_10",
      "label": "Стара Калуђерица",
      "longitude": 20.569555,
      "latitude": 44.759323
    },
    {
      "id": "_11",
      "label": "Чардак",
      "longitude": 20.575949,
      "latitude": 44.756451
    },
    {
      "id": "_12",
      "label": "Хотел Радмиловац",
      "longitude": 20.580799,
      "latitude": 44.753694
    },
    {
      "id": "_13",
      "label": "Петра Кочића",
      "longitude": 20.583959,
      "latitude": 44.750835
    },
    {
      "id": "_14",
      "label": "Душана Петровића Шанета",
      "longitude": 20.587734,
      "latitude": 44.748383
    },
    {
      "id": "_15",
      "label": "Винча /Млин/",
      "longitude": 20.598609,
      "latitude": 44.745502
    },
    {
      "id": "_16",
      "label": "Складиште Боја",
      "longitude": 20.594174,
      "latitude": 44.739288
    },
    {
      "id": "_17",
      "label": "Електродистрибуција",
      "longitude": 20.589052,
      "latitude": 44.734773
    },
    {
      "id": "_18",
      "label": "Стари пут за Болеч",
      "longitude": 20.5839,
      "latitude": 44.73025
    },
    {
      "id": "_19",
      "label": "Раван /Улаз/",
      "longitude": 20.576264,
      "latitude": 44.726802
    },
    {
      "id": "_20",
      "label": "Кремење",
      "longitude": 20.578581,
      "latitude": 44.722302
    },
    {
      "id": "_21",
      "label": "Лештане /Раван/",
      "longitude": 20.583073,
      "latitude": 44.719507
    }
  ],
  "direction_b": [
    {
      "id": "_1",
      "label": "Лештане /Раван/",
      "longitude": 20.583073,
      "latitude": 44.719507
    },
    {
      "id": "_2",
      "label": "Кремење",
      "longitude": 20.578659,
      "latitude": 44.722542
    },
    {
      "id": "_3",
      "label": "Раван /Улаз/",
      "longitude": 20.576293,
      "latitude": 44.727022
    },
    {
      "id": "_4",
      "label": "Лештане /Улаз/",
      "longitude": 20.57585,
      "latitude": 44.72839
    },
    {
      "id": "_5",
      "label": "Лештане",
      "longitude": 20.575387,
      "latitude": 44.730477
    },
    {
      "id": "_6",
      "label": "Стари пут за Болеч",
      "longitude": 20.584415,
      "latitude": 44.730549
    },
    {
      "id": "_7",
      "label": "Електродистрибуција",
      "longitude": 20.589532,
      "latitude": 44.735043
    },
    {
      "id": "_8",
      "label": "Складиште Боја",
      "longitude": 20.594061,
      "latitude": 44.739057
    },
    {
      "id": "_9",
      "label": "Винча /Млин/",
      "longitude": 20.597281,
      "latitude": 44.746075
    },
    {
      "id": "_10",
      "label": "Душана Петровића Шанета",
      "longitude": 20.587041,
      "latitude": 44.748767
    },
    {
      "id": "_11",
      "label": "Петра Кочића",
      "longitude": 20.583749,
      "latitude": 44.751251
    },
    {
      "id": "_12",
      "label": "Хотел Радмиловац",
      "longitude": 20.5808,
      "latitude": 44.753876
    },
    {
      "id": "_13",
      "label": "Чардак",
      "longitude": 20.575664,
      "latitude": 44.756806
    },
    {
      "id": "_14",
      "label": "Стара Калуђерица",
      "longitude": 20.568655,
      "latitude": 44.759998
    },
    {
      "id": "_15",
      "label": "Филипа Кљајића",
      "longitude": 20.565945,
      "latitude": 44.762791
    },
    {
      "id": "_16",
      "label": "Пут за Институт",
      "longitude": 20.564262,
      "latitude": 44.764928
    },
    {
      "id": "_17",
      "label": "Пут за Калуђерицу",
      "longitude": 20.560508,
      "latitude": 44.767865
    },
    {
      "id": "_18",
      "label": "Ново Насеље",
      "longitude": 20.553489,
      "latitude": 44.773034
    },
    {
      "id": "_19",
      "label": "Нине Кирсанове",
      "longitude": 20.548267,
      "latitude": 44.776339
    },
    {
      "id": "_20",
      "label": "ОШ Драгојло Дудић",
      "longitude": 20.533626,
      "latitude": 44.77618
    },
    {
      "id": "_21",
      "label": "Миријевска",
      "longitude": 20.529104,
      "latitude": 44.778136
    },
    {
      "id": "_22",
      "label": "Бајдина",
      "longitude": 20.523552,
      "latitude": 44.781097
    },
    {
      "id": "_23",
      "label": "Устаничка",
      "longitude": 20.517387,
      "latitude": 44.784693
    },
    {
      "id": "_24",
      "label": "Устаничка",
      "longitude": 20.517384,
      "latitude": 44.784813
    }
  ]
}