{
  "direction_a": [
    {
      "id": "_1",
      "label": "Савски трг",
      "longitude": 20.455596,
      "latitude": 44.807795
    },
    {
      "id": "_2",
      "label": "Палата Правде",
      "longitude": 20.452917,
      "latitude": 44.804446
    },
    {
      "id": "_3",
      "label": "Мостар",
      "longitude": 20.448743,
      "latitude": 44.79823
    },
    {
      "id": "_4",
      "label": "Делиградска",
      "longitude": 20.457356,
      "latitude": 44.795314
    },
    {
      "id": "_5",
      "label": "Франше Д'Епереа",
      "longitude": 20.466416,
      "latitude": 44.791513
    },
    {
      "id": "_6",
      "label": "Михајла Гавриловића",
      "longitude": 20.471443,
      "latitude": 44.792105
    },
    {
      "id": "_7",
      "label": "Максима Горког",
      "longitude": 20.479063,
      "latitude": 44.79344
    },
    {
      "id": "_8",
      "label": "Ђердапска",
      "longitude": 20.48487,
      "latitude": 44.793175
    },
    {
      "id": "_9",
      "label": "Грчића Миленка",
      "longitude": 20.489145,
      "latitude": 44.791623
    },
    {
      "id": "_10",
      "label": "Бачванска",
      "longitude": 20.493625,
      "latitude": 44.79088
    },
    {
      "id": "_11",
      "label": "Школа Војислав Илић",
      "longitude": 20.496564,
      "latitude": 44.791218
    },
    {
      "id": "_12",
      "label": "Пијаца Звездара",
      "longitude": 20.504874,
      "latitude": 44.793051
    },
    {
      "id": "_13",
      "label": "Др Велизара Косановића",
      "longitude": 20.508996,
      "latitude": 44.79249
    },
    {
      "id": "_14",
      "label": "Мите Ружића",
      "longitude": 20.514307,
      "latitude": 44.791292
    },
    {
      "id": "_15",
      "label": "Милана Ракића",
      "longitude": 20.517503,
      "latitude": 44.792158
    },
    {
      "id": "_16",
      "label": "Душка Радовића",
      "longitude": 20.520699,
      "latitude": 44.791692
    },
    {
      "id": "_17",
      "label": "Витезова Карађорђеве Звезде",
      "longitude": 20.524457,
      "latitude": 44.792655
    },
    {
      "id": "_18",
      "label": "Селиште",
      "longitude": 20.527516,
      "latitude": 44.790264
    },
    {
      "id": "_19",
      "label": "Стојчино Брдо",
      "longitude": 20.530843,
      "latitude": 44.789233
    },
    {
      "id": "_20",
      "label": "Миријевски Венац",
      "longitude": 20.533601,
      "latitude": 44.789429
    },
    {
      "id": "_21",
      "label": "Миријево 2",
      "longitude": 20.533257,
      "latitude": 44.791106
    },
    {
      "id": "_22",
      "label": "Миријево",
      "longitude": 20.531661,
      "latitude": 44.793657
    }
  ],
  "direction_b": [
    {
      "id": "_1",
      "label": "Миријево",
      "longitude": 20.531119,
      "latitude": 44.793594
    },
    {
      "id": "_2",
      "label": "Миријево 2",
      "longitude": 20.532857,
      "latitude": 44.79135
    },
    {
      "id": "_3",
      "label": "Миријевски Венац",
      "longitude": 20.533356,
      "latitude": 44.789398
    },
    {
      "id": "_4",
      "label": "Стојчино Брдо",
      "longitude": 20.530175,
      "latitude": 44.7894
    },
    {
      "id": "_5",
      "label": "Селиште",
      "longitude": 20.527637,
      "latitude": 44.790556
    },
    {
      "id": "_6",
      "label": "Витезова Карађорђеве Звезде",
      "longitude": 20.525342,
      "latitude": 44.792528
    },
    {
      "id": "_7",
      "label": "Душка Радовића",
      "longitude": 20.52108,
      "latitude": 44.791671
    },
    {
      "id": "_8",
      "label": "Мите Ружића",
      "longitude": 20.513479,
      "latitude": 44.791039
    },
    {
      "id": "_9",
      "label": "Др Велизара Косановића",
      "longitude": 20.510855,
      "latitude": 44.791947
    },
    {
      "id": "_10",
      "label": "Пијаца Звездара",
      "longitude": 20.504825,
      "latitude": 44.793228
    },
    {
      "id": "_11",
      "label": "Школа Војислав Илић",
      "longitude": 20.496881,
      "latitude": 44.791372
    },
    {
      "id": "_12",
      "label": "Бачванска",
      "longitude": 20.494381,
      "latitude": 44.791025
    },
    {
      "id": "_13",
      "label": "Грчића Миленка",
      "longitude": 20.490941,
      "latitude": 44.791443
    },
    {
      "id": "_14",
      "label": "Ђердапска",
      "longitude": 20.486804,
      "latitude": 44.792901
    },
    {
      "id": "_15",
      "label": "МПИ",
      "longitude": 20.481209,
      "latitude": 44.793643
    },
    {
      "id": "_16",
      "label": "Максима Горког",
      "longitude": 20.476673,
      "latitude": 44.793299
    },
    {
      "id": "_17",
      "label": "Михајла Гавриловића",
      "longitude": 20.472156,
      "latitude": 44.792511
    },
    {
      "id": "_18",
      "label": "Франше Д'Епереа",
      "longitude": 20.468232,
      "latitude": 44.790862
    },
    {
      "id": "_19",
      "label": "Делиградска",
      "longitude": 20.457594,
      "latitude": 44.795771
    },
    {
      "id": "_20",
      "label": "Мостар",
      "longitude": 20.449237,
      "latitude": 44.798754
    },
    {
      "id": "_21",
      "label": "Дурмиторска",
      "longitude": 20.451415,
      "latitude": 44.802039
    },
    {
      "id": "_22",
      "label": "Палата Правде",
      "longitude": 20.453787,
      "latitude": 44.804951
    },
    {
      "id": "_23",
      "label": "Савски трг",
      "longitude": 20.456752,
      "latitude": 44.808511
    },
    {
      "id": "_24",
      "label": "Савски трг",
      "longitude": 20.455596,
      "latitude": 44.807795
    }
  ]
}