{
  "direction_a": [
    {
      "id": "_1",
      "label": "Баново Брдо",
      "longitude": 20.413704,
      "latitude": 44.768518
    }
  ],
  "direction_b": [
    {
      "id": "_1",
      "label": "Требевићка",
      "longitude": 20.414341,
      "latitude": 44.771477
    },
    {
      "id": "_2",
      "label": "Петра Лековића",
      "longitude": 20.416964,
      "latitude": 44.771241
    },
    {
      "id": "_3",
      "label": "Жарковачка",
      "longitude": 20.419596,
      "latitude": 44.76815
    },
    {
      "id": "_4",
      "label": "Вртић Бајка",
      "longitude": 20.419403,
      "latitude": 44.765396
    },
    {
      "id": "_5",
      "label": "Миле Јевтовић",
      "longitude": 20.418871,
      "latitude": 44.7622
    },
    {
      "id": "_6",
      "label": "Јована Микића",
      "longitude": 20.42088,
      "latitude": 44.758119
    },
    {
      "id": "_7",
      "label": "Милована Челебића",
      "longitude": 20.424302,
      "latitude": 44.75462
    },
    {
      "id": "_8",
      "label": "Ратка Митровића",
      "longitude": 20.425133,
      "latitude": 44.752856
    },
    {
      "id": "_9",
      "label": "Ане Ахматове",
      "longitude": 20.427944,
      "latitude": 44.749809
    },
    {
      "id": "_10",
      "label": "Ратка Митровића",
      "longitude": 20.430699,
      "latitude": 44.747967
    },
    {
      "id": "_11",
      "label": "Илије Стојадиновића",
      "longitude": 20.4312,
      "latitude": 44.751396
    },
    {
      "id": "_12",
      "label": "Милоја Закића",
      "longitude": 20.429828,
      "latitude": 44.755265
    },
    {
      "id": "_13",
      "label": "Димитрија Аврамовића",
      "longitude": 20.426934,
      "latitude": 44.75883
    },
    {
      "id": "_14",
      "label": "Вртић Кошута",
      "longitude": 20.423298,
      "latitude": 44.757482
    },
    {
      "id": "_15",
      "label": "Јована Микића",
      "longitude": 20.421562,
      "latitude": 44.757621
    },
    {
      "id": "_16",
      "label": "Миле Јевтовић",
      "longitude": 20.41903,
      "latitude": 44.76198
    },
    {
      "id": "_17",
      "label": "Крајишке Бригаде",
      "longitude": 20.416029,
      "latitude": 44.764665
    },
    {
      "id": "_18",
      "label": "Баново Брдо",
      "longitude": 20.413704,
      "latitude": 44.768518
    }
  ]
}