{
  "direction_a": [
    {
      "id": "_1",
      "label": "Ташмајдан /Парк/",
      "longitude": 20.46809,
      "latitude": 44.809599
    },
    {
      "id": "_2",
      "label": "Правни факултет",
      "longitude": 20.472505,
      "latitude": 44.806638
    },
    {
      "id": "_3",
      "label": "Вуков Споменик /бул.Краља Александра/",
      "longitude": 20.478679,
      "latitude": 44.80402
    },
    {
      "id": "_4",
      "label": "ГО Звездара",
      "longitude": 20.482512,
      "latitude": 44.802412
    },
    {
      "id": "_5",
      "label": "Пијаца Стари Ђерам",
      "longitude": 20.487311,
      "latitude": 44.80043
    },
    {
      "id": "_6",
      "label": "Поп Стојанова",
      "longitude": 20.491484,
      "latitude": 44.798674
    },
    {
      "id": "_7",
      "label": "Лион",
      "longitude": 20.495387,
      "latitude": 44.797035
    },
    {
      "id": "_8",
      "label": "Батутова",
      "longitude": 20.499633,
      "latitude": 44.795208
    },
    {
      "id": "_9",
      "label": "Пијаца Звездара",
      "longitude": 20.504874,
      "latitude": 44.793051
    },
    {
      "id": "_10",
      "label": "Др Велизара Косановића",
      "longitude": 20.508996,
      "latitude": 44.79249
    },
    {
      "id": "_11",
      "label": "Мите Ружића",
      "longitude": 20.513379,
      "latitude": 44.790571
    },
    {
      "id": "_12",
      "label": "Косте Трифковића",
      "longitude": 20.51623,
      "latitude": 44.788715
    },
    {
      "id": "_13",
      "label": "Устаничка",
      "longitude": 20.517874,
      "latitude": 44.784611
    }
  ],
  "direction_b": [
    {
      "id": "_1",
      "label": "Устаничка",
      "longitude": 20.517874,
      "latitude": 44.784611
    },
    {
      "id": "_2",
      "label": "Косте Трифковића",
      "longitude": 20.515951,
      "latitude": 44.789227
    },
    {
      "id": "_3",
      "label": "Мите Ружића",
      "longitude": 20.513516,
      "latitude": 44.79067
    },
    {
      "id": "_4",
      "label": "Др Велизара Косановића",
      "longitude": 20.510855,
      "latitude": 44.791947
    },
    {
      "id": "_5",
      "label": "Пијаца Звездара",
      "longitude": 20.504825,
      "latitude": 44.793228
    },
    {
      "id": "_6",
      "label": "Батутова",
      "longitude": 20.498273,
      "latitude": 44.795861
    },
    {
      "id": "_7",
      "label": "Лион",
      "longitude": 20.49462,
      "latitude": 44.797439
    },
    {
      "id": "_8",
      "label": "Поп Стојанова",
      "longitude": 20.489926,
      "latitude": 44.799418
    },
    {
      "id": "_9",
      "label": "Пијаца Стари Ђерам",
      "longitude": 20.486227,
      "latitude": 44.800967
    },
    {
      "id": "_10",
      "label": "ГО Звездара",
      "longitude": 20.48241,
      "latitude": 44.802551
    },
    {
      "id": "_11",
      "label": "Вуков Споменик /бул.Краља Александра/",
      "longitude": 20.477708,
      "latitude": 44.804518
    },
    {
      "id": "_12",
      "label": "Правни факултет",
      "longitude": 20.470925,
      "latitude": 44.807531
    },
    {
      "id": "_13",
      "label": "Ташмајдан /Парк/",
      "longitude": 20.46809,
      "latitude": 44.809599
    }
  ]
}